bunny_sdk/__init__.py
bunny_sdk/bunny_api_client/abusecase/abusecase_get_response.py
bunny_sdk/bunny_api_client/abusecase/abusecase_request_builder.py
bunny_sdk/bunny_api_client/abusecase/item/abusecase_item_request_builder.py
bunny_sdk/bunny_api_client/abusecase/item/check/check_request_builder.py
bunny_sdk/bunny_api_client/abusecase/item/resolve/resolve_request_builder.py
bunny_sdk/bunny_api_client/apikey/apikey_get_response.py
bunny_sdk/bunny_api_client/apikey/apikey_request_builder.py
bunny_sdk/bunny_api_client/billing/affiliate/affiliate_request_builder.py
bunny_sdk/bunny_api_client/billing/affiliate/claim/claim_request_builder.py
bunny_sdk/bunny_api_client/billing/billing_request_builder.py
bunny_sdk/bunny_api_client/bunny_api_client.py
bunny_sdk/bunny_api_client/compute/compute_request_builder.py
bunny_sdk/bunny_api_client/compute/script/item/code/code_get_response.py
bunny_sdk/bunny_api_client/compute/script/item/code/code_post_request_body.py
bunny_sdk/bunny_api_client/compute/script/item/code/code_request_builder.py
bunny_sdk/bunny_api_client/compute/script/item/publish/item/with_uu_item_request_builder.py
bunny_sdk/bunny_api_client/compute/script/item/publish/item/with_uu_post_request_body.py
bunny_sdk/bunny_api_client/compute/script/item/publish/publish_post_request_body.py
bunny_sdk/bunny_api_client/compute/script/item/publish/publish_request_builder.py
bunny_sdk/bunny_api_client/compute/script/item/releases/releases_get_response.py
bunny_sdk/bunny_api_client/compute/script/item/releases/releases_request_builder.py
bunny_sdk/bunny_api_client/compute/script/item/script_item_request_builder.py
bunny_sdk/bunny_api_client/compute/script/item/variables/add/add_request_builder.py
bunny_sdk/bunny_api_client/compute/script/item/variables/item/with_variable_item_request_builder.py
bunny_sdk/bunny_api_client/compute/script/item/variables/variables_request_builder.py
bunny_sdk/bunny_api_client/compute/script/script_get_response.py
bunny_sdk-0.0.16.dist-info/LICENSE.txt
bunny_sdk-0.0.16.dist-info/METADATA
bunny_sdk-0.0.16.dist-info/WHEEL
bunny_sdk-0.0.16.dist-info/RECORD
