Metadata-Version: 2.1
Name: bunny-sdk
Version: 0.0.16
Summary: Python SDK for bunny.net 🐰
License: AGPL-3.0-only
Keywords: BunnyCDN,bunny.net,bunny,cdn,bunny-launcher,sdk,api
Author: John L. Armstrong IV
Requires-Python: >=3.8,<4.0
Classifier: License :: OSI Approved :: GNU Affero General Public License v3
Classifier: Programming Language :: Python :: 3
Classifier: Programming Language :: Python :: 3.8
Classifier: Programming Language :: Python :: 3.9
Classifier: Programming Language :: Python :: 3.10
Classifier: Programming Language :: Python :: 3.11
Classifier: Programming Language :: Python :: 3.12
Requires-Dist: microsoft-kiota-abstractions (==1.6.0)
Requires-Dist: microsoft-kiota-http (==1.6.0)
Requires-Dist: microsoft-kiota-serialization-form (==1.6.0)
Requires-Dist: microsoft-kiota-serialization-json (==1.6.0)
Requires-Dist: microsoft-kiota-serialization-multipart (==1.6.0)
Requires-Dist: microsoft-kiota-serialization-text (==1.6.0)
Requires-Dist: urllib3 (>=2.2.3,<3.0.0)
Project-URL: Changelog, https://github.com/jlarmstrongiv/bunny-sdk-python/commits/main/
Project-URL: Documentation, https://bunny-launcher.net/bunny-sdk/languages/python/
Project-URL: Homepage, https://bunny-launcher.net/bunny-sdk/languages/python/
Project-URL: Issues, https://github.com/jlarmstrongiv/bunny-sdk-python/issues
Project-URL: Repository, https://github.com/jlarmstrongiv/bunny-sdk-python.git
